agentlib/__init__.py
agentlib/memorytool.py
geogpt_agent_lib-0.1.dist-info/METADATA
geogpt_agent_lib-0.1.dist-info/WHEEL
geogpt_agent_lib-0.1.dist-info/top_level.txt
geogpt_agent_lib-0.1.dist-info/RECORD
