Metadata-Version: 2.1
Name: geogpt-agent-lib
Version: 0.1
Summary: geogpt agent library
Author: geogpt
Author-email: zhuquezhitu@zhejianglab.com
License: UNKNOWN
Platform: UNKNOWN
Requires-Python: >=3.6
